<?xml version="1.0" encoding="UTF-8"?>
<facsimile xmlns="http://www.tei-c.org/ns/1.0" xml:id="letter_0231_facs">
   <surface xml:id="letter_0231_001_facs"
            ulx="0"
            uly="0"
            lrx="5240"
            lry="6712">
      <graphic url="https://www.monacensia-digital.de/i3f/v20/415717"
               width="5240"
               height="6712"/>
      <zone xml:id="letter_0231_001_tr_1"
            points="1421,553 5004,553 5004,6345 1421,6345"
            rendition="TextRegion">
         <zone xml:id="letter_0231_001_tr_1_tl_1"
               points="2622,650 2905,721 3276,632 3692,712 4112,654 4611,747 4943,721 4939,504 4638,535 4417,438 3944,561 3334,416 2922,517 2622,482"
               rendition="TextLine"/>
         <zone xml:id="letter_0231_001_tr_1_tl_2"
               points="3431,800 3533,831 3656,805 3776,840 3851,822 3917,862 3984,805 4085,849 4076,663 3975,690 3957,672 3860,716 3776,681 3692,712 3603,654 3524,694 3426,690"
               rendition="TextLine"/>
         <zone xml:id="letter_0231_001_tr_1_tl_3"
               points="1477,1428 4054,1455 4908,1592 4899,1424 4076,1397 3838,1282 3740,1371 3258,1295 3082,1379 2874,1273 1990,1335 1468,1242"
               rendition="TextLine"/>
         <zone xml:id="letter_0231_001_tr_1_tl_4"
               points="1481,1592 2317,1592 2586,1711 3338,1654 4045,1746 4222,1671 4709,1795 4713,1587 3590,1609 3263,1481 2520,1570 1963,1410 1477,1512"
               rendition="TextLine"/>
         <zone xml:id="letter_0231_001_tr_1_tl_5"
               points="1432,1795 3316,1932 3709,1853 4205,1994 4890,1941 4726,1768 4183,1853 3816,1738 1428,1689"
               rendition="TextLine"/>
         <zone xml:id="letter_0231_001_tr_1_tl_6"
               points="1463,2029 2197,1963 2507,2096 2679,2007 4952,2215 4939,2029 4510,1937 4386,2025 3572,2012 1446,1786"
               rendition="TextLine"/>
         <zone xml:id="letter_0231_001_tr_1_tl_7"
               points="1437,2202 2511,2175 4819,2418 4735,2219 4541,2290 3758,2118 3272,2180 2600,2047 1428,2056"
               rendition="TextLine"/>
         <zone xml:id="letter_0231_001_tr_1_tl_8"
               points="1472,2330 4859,2586 4846,2454 4381,2321 4103,2458 3515,2317 1459,2206"
               rendition="TextLine"/>
         <zone xml:id="letter_0231_001_tr_1_tl_9"
               points="1410,2622 1950,2520 2105,2609 2604,2560 4549,2746 4536,2560 3953,2613 3665,2485 3002,2564 2445,2405 1393,2418"
               rendition="TextLine"/>
         <zone xml:id="letter_0231_001_tr_1_tl_10"
               points="1450,2763 2118,2715 2471,2825 2807,2754 4992,2962 4983,2816 4103,2723 3639,2785 2772,2626 1441,2622"
               rendition="TextLine"/>
         <zone xml:id="letter_0231_001_tr_1_tl_11"
               points="1415,2914 4766,3144 4598,2989 4116,2883 3829,2967 2127,2768 1406,2794"
               rendition="TextLine"/>
         <zone xml:id="letter_0231_001_tr_1_tl_12"
               points="1424,3077 4735,3338 4717,3139 4098,3219 3776,3099 3236,3135 3051,3015 1410,2940"
               rendition="TextLine"/>
         <zone xml:id="letter_0231_001_tr_1_tl_13"
               points="1459,3334 2670,3312 3135,3453 3736,3426 4006,3546 4169,3457 4921,3603 4908,3426 4306,3418 3678,3228 3577,3320 2927,3192 2688,3285 1441,3135"
               rendition="TextLine"/>
         <zone xml:id="letter_0231_001_tr_1_tl_14"
               points="1402,3510 2905,3528 3042,3617 4050,3643 4390,3785 4837,3749 4819,3555 4687,3515 3634,3564 3020,3396 2617,3462 2387,3356 2003,3422 1384,3325"
               rendition="TextLine"/>
         <zone xml:id="letter_0231_001_tr_1_tl_15"
               points="1428,3709 1972,3789 2352,3692 3029,3732 3325,3873 4700,3948 4691,3816 4032,3670 3550,3754 2980,3590 1410,3519"
               rendition="TextLine"/>
         <zone xml:id="letter_0231_001_tr_1_tl_16"
               points="1450,3877 1516,3882 1525,3864 1556,3891 1627,3900 1720,3873 1804,3900 1839,3882 1888,3891 1883,3820 1822,3838 1715,3771 1671,3771 1583,3709 1534,3705 1494,3754 1441,3745"
               rendition="TextLine"/>
         <zone xml:id="letter_0231_001_tr_1_tl_17"
               points="1481,4085 3568,4147 4037,4302 4249,4227 4921,4333 4899,4063 4191,4169 3444,3992 1472,3917"
               rendition="TextLine"/>
         <zone xml:id="letter_0231_001_tr_1_tl_18"
               points="1512,4289 2100,4227 2909,4373 3462,4337 4435,4452 4598,4580 4810,4488 3904,4236 3652,4320 3466,4227 1499,4107"
               rendition="TextLine"/>
         <zone xml:id="letter_0231_001_tr_1_tl_19"
               points="1490,4417 4850,4682 4806,4492 4603,4580 3183,4364 2644,4417 2158,4240 1486,4328"
               rendition="TextLine"/>
         <zone xml:id="letter_0231_001_tr_1_tl_20"
               points="1499,4633 2352,4589 2564,4687 2763,4625 4801,4859 4793,4766 4399,4647 1791,4435 1486,4501"
               rendition="TextLine"/>
         <zone xml:id="letter_0231_001_tr_1_tl_21"
               points="1539,4784 3042,4828 4160,5049 4899,5027 4894,4912 4258,4899 3727,4740 1525,4629"
               rendition="TextLine"/>
         <zone xml:id="letter_0231_001_tr_1_tl_22"
               points="1534,4925 4885,5226 4872,5084 4625,5045 1521,4797"
               rendition="TextLine"/>
         <zone xml:id="letter_0231_001_tr_1_tl_23"
               points="1556,5089 4850,5420 4837,5275 4174,5168 3042,5137 2573,4974 1547,4987"
               rendition="TextLine"/>
         <zone xml:id="letter_0231_001_tr_1_tl_24"
               points="1508,5297 1963,5350 2065,5306 2542,5438 2688,5332 2679,5208 2361,5248 2193,5146 2038,5199 1729,5098 1499,5213"
               rendition="TextLine"/>
         <zone xml:id="letter_0231_001_tr_1_tl_25"
               points="1570,5482 2489,5465 3029,5593 3289,5513 3873,5655 4700,5677 4687,5447 4293,5553 3736,5390 1561,5359"
               rendition="TextLine"/>
         <zone xml:id="letter_0231_001_tr_1_tl_26"
               points="1561,5686 2759,5677 3064,5774 3378,5703 4501,5827 4492,5672 4302,5633 3705,5703 3502,5593 3174,5637 2856,5527 2768,5619 2166,5504 1552,5558"
               rendition="TextLine"/>
         <zone xml:id="letter_0231_001_tr_1_tl_27"
               points="1556,5863 2582,5871 3152,5986 4244,5933 4479,6013 4496,5867 4125,5779 3652,5871 3378,5774 3073,5818 2861,5703 2237,5796 1547,5730"
               rendition="TextLine"/>
         <zone xml:id="letter_0231_001_tr_1_tl_28"
               points="1552,6106 3011,6066 4448,6212 4443,6031 4085,5960 1543,5898"
               rendition="TextLine"/>
         <zone xml:id="letter_0231_001_tr_1_tl_29"
               points="1565,6221 2648,6300 2874,6393 2998,6305 3413,6309 3908,6415 4368,6353 4373,6221 1561,6168"
               rendition="TextLine"/>
      </zone>
   </surface>
   <surface xml:id="letter_0231_002_facs"
            ulx="0"
            uly="0"
            lrx="5240"
            lry="6712">
      <graphic url="https://www.monacensia-digital.de/i3f/v20/415718"
               width="5240"
               height="6712"/>
      <zone xml:id="letter_0231_002_tr_1"
            points="1242,648 5022,648 5022,6286 1242,6286"
            rendition="TextRegion">
         <zone xml:id="letter_0231_002_tr_1_tl_1"
               points="1289,805 1652,707 2894,861 3126,777 4550,907 4848,837 4843,730 3689,628 3592,716 2298,582 1684,670 1279,507"
               rendition="TextLine"/>
         <zone xml:id="letter_0231_002_tr_1_tl_2"
               points="1303,935 1466,893 1596,935 1698,884 1838,954 1894,917 2373,940 2368,763 2126,805 2033,758 1935,851 1787,810 1670,833 1619,786 1549,819 1470,758 1298,805"
               rendition="TextLine"/>
         <zone xml:id="letter_0231_002_tr_1_tl_3"
               points="1284,1070 4839,1233 4834,1084 4299,1107 4113,1000 3443,1079 2712,917 1279,944"
               rendition="TextLine"/>
         <zone xml:id="letter_0231_002_tr_1_tl_4"
               points="1293,1284 2908,1256 3685,1382 3964,1321 4331,1447 4601,1396 4592,1191 1284,1117"
               rendition="TextLine"/>
         <zone xml:id="letter_0231_002_tr_1_tl_5"
               points="1256,1382 1386,1414 1438,1400 1484,1428 1554,1391 1726,1433 1768,1391 1796,1391 1791,1335 1726,1335 1638,1270 1517,1279 1475,1252 1396,1252 1252,1340"
               rendition="TextLine"/>
         <zone xml:id="letter_0231_002_tr_1_tl_6"
               points="1252,1549 4699,1740 4690,1479 3271,1545 2573,1433 2336,1535 2108,1433 1242,1428"
               rendition="TextLine"/>
         <zone xml:id="letter_0231_002_tr_1_tl_7"
               points="1261,1782 4885,1921 4876,1763 4573,1726 1252,1619"
               rendition="TextLine"/>
         <zone xml:id="letter_0231_002_tr_1_tl_8"
               points="1298,1945 2080,1889 3699,1991 3871,2098 4038,2015 4787,2084 4685,1908 4350,1968 3820,1833 3624,1931 3243,1824 3029,1898 1289,1787"
               rendition="TextLine"/>
         <zone xml:id="letter_0231_002_tr_1_tl_9"
               points="1284,2084 4699,2243 4690,2094 4294,2047 4155,2117 2480,1926 1275,1935"
               rendition="TextLine"/>
         <zone xml:id="letter_0231_002_tr_1_tl_10"
               points="1275,2266 5011,2447 5006,2331 4429,2224 3787,2215 3680,2308 3154,2154 1265,2084"
               rendition="TextLine"/>
         <zone xml:id="letter_0231_002_tr_1_tl_11"
               points="1279,2489 1493,2396 4825,2615 4671,2489 4211,2498 4024,2382 3694,2484 3378,2359 1265,2280"
               rendition="TextLine"/>
         <zone xml:id="letter_0231_002_tr_1_tl_12"
               points="1303,2638 2992,2633 3201,2745 3550,2689 4727,2852 4713,2652 4276,2708 3438,2536 3271,2615 3159,2522 1289,2480"
               rendition="TextLine"/>
         <zone xml:id="letter_0231_002_tr_1_tl_13"
               points="1252,2773 2182,2866 2577,2796 4652,3061 4634,2838 4443,2810 3261,2819 2703,2633 1824,2717 1242,2629"
               rendition="TextLine"/>
         <zone xml:id="letter_0231_002_tr_1_tl_14"
               points="1242,3001 2750,3006 3387,3150 4843,3215 4834,3066 1228,2824"
               rendition="TextLine"/>
         <zone xml:id="letter_0231_002_tr_1_tl_15"
               points="1219,3154 4778,3396 4769,3257 3731,3257 2633,3047 1205,2978"
               rendition="TextLine"/>
         <zone xml:id="letter_0231_002_tr_1_tl_16"
               points="1265,3313 3741,3503 4773,3731 4890,3657 4871,3438 3983,3480 3606,3313 1261,3247"
               rendition="TextLine"/>
         <zone xml:id="letter_0231_002_tr_1_tl_17"
               points="1238,3545 4811,3806 4801,3703 4336,3624 1224,3373"
               rendition="TextLine"/>
         <zone xml:id="letter_0231_002_tr_1_tl_18"
               points="1233,3699 4839,4020 4825,3871 4034,3731 1219,3550"
               rendition="TextLine"/>
         <zone xml:id="letter_0231_002_tr_1_tl_19"
               points="1261,3941 2908,3983 4620,4197 4606,3996 4159,3931 3629,3983 1242,3717"
               rendition="TextLine"/>
         <zone xml:id="letter_0231_002_tr_1_tl_20"
               points="1317,4117 4946,4350 4936,4238 4350,4145 1870,4048 1298,3899"
               rendition="TextLine"/>
         <zone xml:id="letter_0231_002_tr_1_tl_21"
               points="1252,4299 4657,4559 4643,4401 3745,4276 1238,4127"
               rendition="TextLine"/>
         <zone xml:id="letter_0231_002_tr_1_tl_22"
               points="1293,4541 2564,4518 2731,4615 3085,4555 3285,4666 4829,4741 4820,4587 1279,4345"
               rendition="TextLine"/>
         <zone xml:id="letter_0231_002_tr_1_tl_23"
               points="1317,4746 2094,4694 4894,4964 4880,4811 4383,4699 3727,4746 2522,4550 1987,4648 1698,4504 1298,4541"
               rendition="TextLine"/>
         <zone xml:id="letter_0231_002_tr_1_tl_24"
               points="1312,4927 1759,4871 2740,5053 3229,4987 3959,5136 4197,5057 4615,5211 4741,5113 4997,5164 4890,4992 2610,4857 2433,4746 1303,4806"
               rendition="TextLine"/>
         <zone xml:id="letter_0231_002_tr_1_tl_25"
               points="1298,5090 1554,5164 1759,5057 2275,5113 2461,5225 2847,5229 2992,5155 3773,5234 3764,5155 3536,5085 3252,5099 2996,5001 2461,5067 2149,4960 1805,5001 1624,4894 1289,4941"
               rendition="TextLine"/>
         <zone xml:id="letter_0231_002_tr_1_tl_26"
               points="1312,5355 1628,5276 2108,5388 4773,5490 4764,5360 4448,5318 1298,5146"
               rendition="TextLine"/>
         <zone xml:id="letter_0231_002_tr_1_tl_27"
               points="1307,5546 1600,5462 2140,5574 2401,5513 4634,5690 4625,5555 4094,5485 3782,5555 3233,5411 1293,5388"
               rendition="TextLine"/>
         <zone xml:id="letter_0231_002_tr_1_tl_28"
               points="1317,5727 2294,5709 4960,5969 4941,5723 1303,5555"
               rendition="TextLine"/>
         <zone xml:id="letter_0231_002_tr_1_tl_29"
               points="1298,5862 2154,6011 4341,6067 4615,6216 4615,5918 4411,6025 3996,5913 3489,5974 2945,5788 2475,5871 2238,5760 1284,5713"
               rendition="TextLine"/>
         <zone xml:id="letter_0231_002_tr_1_tl_30"
               points="1349,6081 4308,6318 4304,6155 3615,6174 3317,6025 2852,6109 2377,5969 1912,6039 1335,5904"
               rendition="TextLine"/>
      </zone>
   </surface>
   <surface xml:id="letter_0231_003_facs"
            ulx="0"
            uly="0"
            lrx="5240"
            lry="6712">
      <graphic url="https://www.monacensia-digital.de/i3f/v20/415719"
               width="5240"
               height="6712"/>
      <zone xml:id="letter_0231_003_r"
            points="1224,690 4974,690 4974,4291 4317,6220 1910,6220 1224,4291"
            rendition="TextRegion">
         <zone xml:id="letter_0231_003_tr_1_tl_1"
               points="1318,760 1657,870 3291,879 3740,1016 4289,920 4751,1048 4733,742 4536,673 3364,806 1314,655"
               rendition="TextLine"/>
         <zone xml:id="letter_0231_003_tr_1_tl_2"
               points="1350,1012 2225,993 3918,1213 4610,1186 4628,1021 4307,1089 4060,966 3470,1035 2994,897 2719,993 2508,865 2087,943 1767,842 1341,879"
               rendition="TextLine"/>
         <zone xml:id="letter_0231_003_tr_1_tl_3"
               points="1341,1231 1570,1149 1680,1186 1849,1158 1959,1231 2083,1199 2161,1263 2238,1218 2531,1227 2522,1112 2211,1085 2156,1117 2014,1048 1895,1103 1749,1048 1566,1094 1501,1053 1327,1071"
               rendition="TextLine"/>
         <zone xml:id="letter_0231_003_tr_1_tl_4"
               points="1341,1341 4669,1598 4660,1446 3891,1456 3383,1282 3122,1392 1332,1245"
               rendition="TextLine"/>
         <zone xml:id="letter_0231_003_tr_1_tl_5"
               points="1314,1575 4445,1753 4431,1584 3310,1620 2550,1414 1620,1474 1305,1392"
               rendition="TextLine"/>
         <zone xml:id="letter_0231_003_tr_1_tl_6"
               points="1327,1749 2664,1904 2920,1831 3186,1945 3754,1895 4001,2014 4536,1959 4532,1840 4065,1771 3799,1858 2943,1680 2769,1771 2293,1634 2083,1712 1318,1620"
               rendition="TextLine"/>
         <zone xml:id="letter_0231_003_tr_1_tl_7"
               points="1337,1955 4266,2124 4454,2216 4724,2147 4715,2010 4587,1987 4014,2055 1327,1781"
               rendition="TextLine"/>
         <zone xml:id="letter_0231_003_tr_1_tl_8"
               points="1309,2161 4591,2357 4578,2188 1300,2010"
               rendition="TextLine"/>
         <zone xml:id="letter_0231_003_tr_1_tl_9"
               points="1337,2344 4889,2605 4875,2435 4632,2408 3296,2394 2348,2206 1327,2257"
               rendition="TextLine"/>
         <zone xml:id="letter_0231_003_tr_1_tl_10"
               points="2261,2650 2875,2632 3548,2769 3758,2714 4083,2829 4349,2769 4632,2879 4916,2811 4843,2655 4106,2591 3969,2687 3374,2508 2678,2568 2385,2463 2252,2541"
               rendition="TextLine"/>
         <zone xml:id="letter_0231_003_tr_1_tl_11"
               points="1295,2861 2074,2934 2188,2829 2632,2829 3021,2962 3218,2856 4010,3030 4234,2966 4509,3104 4962,3058 4948,2888 4825,2870 1277,2623"
               rendition="TextLine"/>
         <zone xml:id="letter_0231_003_tr_1_tl_12"
               points="1300,2971 1607,2962 1739,3049 2330,3012 2550,3104 2742,3030 3177,3067 3168,2943 2728,2989 2499,2861 2074,2934 1991,2879 1868,2939 1698,2843 1295,2866"
               rendition="TextLine"/>
         <zone xml:id="letter_0231_003_tr_1_tl_13"
               points="1282,3158 1556,3255 1904,3195 2490,3319 2678,3236 4413,3401 4417,3273 4216,3209 4005,3277 3813,3172 3117,3209 2463,3049 2138,3149 1703,3026 1273,3049"
               rendition="TextLine"/>
         <zone xml:id="letter_0231_003_tr_1_tl_14"
               points="1327,3465 2019,3415 4536,3607 4523,3415 3722,3461 3323,3337 1314,3255"
               rendition="TextLine"/>
         <zone xml:id="letter_0231_003_tr_1_tl_15"
               points="1341,3657 1836,3667 1959,3616 2060,3648 2156,3616 2632,3712 2623,3566 2536,3616 2298,3497 2211,3552 2032,3483 1685,3538 1547,3465 1327,3461"
               rendition="TextLine"/>
         <zone xml:id="letter_0231_003_tr_1_tl_16"
               points="1204,3850 1524,3781 2055,3914 3232,3895 4481,4120 4463,3873 3969,3804 1190,3685"
               rendition="TextLine"/>
         <zone xml:id="letter_0231_003_tr_1_tl_17"
               points="1350,4019 4669,4335 4646,4101 3502,4065 3158,3946 2843,4056 2582,3946 2357,4019 1923,3859 1332,3836"
               rendition="TextLine"/>
         <zone xml:id="letter_0231_003_tr_2_tl_1"
               points="1904,4513 2101,4431 2852,4646 3319,4596 4271,4692 4252,4536 4170,4518 4014,4596 2930,4330 2412,4326 2257,4243 1877,4294"
               rendition="TextLine"/>
         <zone xml:id="letter_0231_003_tr_2_tl_2"
               points="1913,4637 2023,4619 2106,4651 2188,4628 2257,4669 2353,4646 2330,4513 2147,4500 2032,4454 1968,4500 1895,4504"
               rendition="TextLine"/>
         <zone xml:id="letter_0231_003_tr_2_tl_3"
               points="2064,4880 2371,4820 2742,4930 2843,4893 3049,5003 3126,4957 3813,5022 4083,5136 4230,5086 4220,4976 3932,4980 3483,4811 3076,4861 2765,4747 2037,4687"
               rendition="TextLine"/>
         <zone xml:id="letter_0231_003_tr_2_tl_4"
               points="2087,5012 3213,5191 3337,5273 3648,5228 3923,5351 4271,5296 4243,5104 3305,5022 2939,5063 2733,4957 2458,4985 2069,4870"
               rendition="TextLine"/>
         <zone xml:id="letter_0231_003_tr_2_tl_5"
               points="2096,5228 2211,5195 2348,5287 2481,5241 2884,5397 3209,5337 3735,5488 3923,5424 4230,5484 4211,5337 3992,5292 3854,5379 3548,5241 3360,5278 3053,5173 2705,5159 2582,5209 2074,5063"
               rendition="TextLine"/>
         <zone xml:id="letter_0231_003_tr_2_tl_6"
               points="2078,5383 4019,5635 4129,5708 4312,5676 4289,5520 3593,5429 3419,5516 2907,5429 2595,5292 2064,5292"
               rendition="TextLine"/>
         <zone xml:id="letter_0231_003_tr_2_tl_7"
               points="2078,5607 2248,5607 2476,5699 2852,5749 3268,5873 3474,5832 3442,5603 3236,5530 3154,5589 2898,5488 2797,5543 2403,5466 2298,5530 2064,5488"
               rendition="TextLine"/>
         <zone xml:id="letter_0231_003_tr_2_tl_8"
               points="3378,6010 3561,6010 3653,6051 3689,6047 3657,5832 3575,5878 3479,5855 3442,5827 3351,5836"
               rendition="TextLine"/>
         <zone xml:id="letter_0231_003_tr_2_tl_9"
               points="3781,6207 3822,6212 3836,6198 3863,6225 3905,6230 3932,6198 4010,6248 4065,6235 4047,6070 3996,6079 3950,6061 3927,6088 3882,6070 3813,6106 3790,6083 3767,6088"
               rendition="TextLine"/>
      </zone>
   </surface>
</facsimile>
