<?xml version="1.0" encoding="UTF-8"?>
<facsimile xmlns="http://www.tei-c.org/ns/1.0" xml:id="smallform_0033_facs">
   <surface xml:id="smallform_0033_001_facs"
            ulx="0"
            uly="0"
            lrx="3664"
            lry="5520">
      <graphic url="https://iiif.ub.unibe.ch/image/v3/schwarzenbach/smallform_0033_001.png/info.json"
               width="3664"
               height="5520"/>
      <zone xml:id="smallform_0033_001_r"
            points="2703,456 3575,456 3575,4049 2703,4049"
            rendition="TextRegion">
         <zone xml:id="smallform_0033_001_l"
               points="2766,544 3495,531 3495,476 3287,496 3161,474 3021,507 2966,478 2766,484"
               rendition="TextLine"/>
         <zone xml:id="smallform_0033_001_l_7"
               points="2753,592 3530,588 3552,535 3302,571 3212,544 2753,557"
               rendition="TextLine"/>
         <zone xml:id="smallform_0033_001_l_11"
               points="2701,623 3556,617 3528,585 3433,581 2701,592"
               rendition="TextLine"/>
         <zone xml:id="smallform_0033_001_l_15"
               points="2708,665 3553,653 3553,616 2708,627"
               rendition="TextLine"/>
         <zone xml:id="smallform_0033_001_l_19"
               points="2703,692 3521,698 3552,654 2703,666"
               rendition="TextLine"/>
         <zone xml:id="smallform_0033_001_l_23"
               points="2704,734 3558,732 3558,685 2704,696"
               rendition="TextLine"/>
         <zone xml:id="smallform_0033_001_l_27"
               points="2701,765 3529,762 3559,736 2701,735"
               rendition="TextLine"/>
         <zone xml:id="smallform_0033_001_l_31"
               points="2697,795 3559,800 3551,753 2697,764"
               rendition="TextLine"/>
         <zone xml:id="smallform_0033_001_l_35"
               points="2706,836 3491,836 3548,820 3549,788 2707,800"
               rendition="TextLine"/>
         <zone xml:id="smallform_0033_001_l_39"
               points="2703,862 3557,851 3525,819 2703,837"
               rendition="TextLine"/>
         <zone xml:id="smallform_0033_001_l_43"
               points="2703,902 3562,886 3550,850 3486,874 2703,865"
               rendition="TextLine"/>
         <zone xml:id="smallform_0033_001_l_47"
               points="2704,933 3563,935 3563,891 3479,885 2704,902"
               rendition="TextLine"/>
         <zone xml:id="smallform_0033_001_l_51"
               points="2707,967 3557,957 3491,925 2707,933"
               rendition="TextLine"/>
         <zone xml:id="smallform_0033_001_l_55"
               points="2699,1001 3554,1001 3554,957 3025,985 2699,964"
               rendition="TextLine"/>
         <zone xml:id="smallform_0033_001_l_59"
               points="2699,1033 3328,1024 3395,1062 3559,1062 3560,1002 3535,997 2700,1005"
               rendition="TextLine"/>
         <zone xml:id="smallform_0033_001_l_63"
               points="2704,1069 3330,1084 3554,1063 3556,1025 2704,1035"
               rendition="TextLine"/>
         <zone xml:id="smallform_0033_001_l_67"
               points="2713,1106 3547,1096 3529,1063 2713,1067"
               rendition="TextLine"/>
         <zone xml:id="smallform_0033_001_l_71"
               points="2709,1134 3568,1127 3550,1090 2709,1105"
               rendition="TextLine"/>
         <zone xml:id="smallform_0033_001_l_75"
               points="2707,1171 3442,1169 3552,1161 3553,1130 2708,1133"
               rendition="TextLine"/>
         <zone xml:id="smallform_0033_001_l_79"
               points="2704,1206 3552,1193 3546,1160 2704,1173"
               rendition="TextLine"/>
         <zone xml:id="smallform_0033_001_l_83"
               points="2702,1243 3481,1241 3558,1229 3559,1196 2703,1207"
               rendition="TextLine"/>
         <zone xml:id="smallform_0033_001_l_87"
               points="2702,1267 3556,1268 3542,1227 2702,1243"
               rendition="TextLine"/>
         <zone xml:id="smallform_0033_001_l_91"
               points="2704,1305 3558,1297 3558,1268 3507,1261 2704,1272"
               rendition="TextLine"/>
         <zone xml:id="smallform_0033_001_l_95"
               points="2704,1341 3558,1330 3531,1295 2704,1306"
               rendition="TextLine"/>
         <zone xml:id="smallform_0033_001_l_99"
               points="2700,1368 3560,1370 3560,1330 2700,1345"
               rendition="TextLine"/>
         <zone xml:id="smallform_0033_001_l_103"
               points="2709,1406 3557,1407 3558,1373 2710,1370"
               rendition="TextLine"/>
         <zone xml:id="smallform_0033_001_l_107"
               points="2704,1438 3558,1430 3534,1397 2704,1403"
               rendition="TextLine"/>
         <zone xml:id="smallform_0033_001_l_111"
               points="2704,1476 3558,1471 3547,1428 2704,1438"
               rendition="TextLine"/>
         <zone xml:id="smallform_0033_001_l_115"
               points="2707,1508 3528,1505 3563,1474 2708,1478"
               rendition="TextLine"/>
         <zone xml:id="smallform_0033_001_l_119"
               points="2702,1544 3562,1539 3562,1502 3506,1497 2702,1512"
               rendition="TextLine"/>
         <zone xml:id="smallform_0033_001_l_123"
               points="2702,1578 3564,1570 3557,1532 2703,1545"
               rendition="TextLine"/>
         <zone xml:id="smallform_0033_001_l_127"
               points="2702,1610 3557,1607 3542,1564 2703,1578"
               rendition="TextLine"/>
         <zone xml:id="smallform_0033_001_l_131"
               points="2700,1639 3551,1642 3560,1610 2701,1607"
               rendition="TextLine"/>
         <zone xml:id="smallform_0033_001_l_135"
               points="2704,1677 3558,1671 3513,1631 2704,1642"
               rendition="TextLine"/>
         <zone xml:id="smallform_0033_001_l_208"
               points="2702,1708 3564,1711 3545,1667 2702,1678"
               rendition="TextLine"/>
         <zone xml:id="smallform_0033_001_l_212"
               points="2704,1739 3559,1744 3535,1701 2704,1708"
               rendition="TextLine"/>
         <zone xml:id="smallform_0033_001_l_216"
               points="2699,1776 3561,1778 3549,1741 2699,1745"
               rendition="TextLine"/>
         <zone xml:id="smallform_0033_001_l_220"
               points="2704,1816 3558,1800 3519,1770 2704,1794"
               rendition="TextLine"/>
         <zone xml:id="smallform_0033_001_l_224"
               points="2702,1846 3561,1867 3561,1798 2702,1817"
               rendition="TextLine"/>
         <zone xml:id="smallform_0033_001_l_228"
               points="2709,1884 3562,1875 3562,1839 3413,1862 3373,1840 2709,1844"
               rendition="TextLine"/>
         <zone xml:id="smallform_0033_001_l_232"
               points="2700,1913 3429,1913 3561,1904 3562,1875 2700,1880"
               rendition="TextLine"/>
         <zone xml:id="smallform_0033_001_l_236"
               points="2707,1951 3560,1940 3552,1903 2707,1912"
               rendition="TextLine"/>
         <zone xml:id="smallform_0033_001_l_240"
               points="2704,1984 3472,1977 3417,1940 2706,1953"
               rendition="TextLine"/>
         <zone xml:id="smallform_0033_001_l_244"
               points="2760,2027 3559,2015 3542,1970 2760,1988"
               rendition="TextLine"/>
         <zone xml:id="smallform_0033_001_l_248"
               points="2704,2057 3559,2051 3559,2014 3066,2037 2704,2013"
               rendition="TextLine"/>
         <zone xml:id="smallform_0033_001_l_252"
               points="2704,2089 3492,2087 3567,2058 2706,2059"
               rendition="TextLine"/>
         <zone xml:id="smallform_0033_001_l_256"
               points="2698,2120 3562,2118 3562,2090 3511,2080 2698,2095"
               rendition="TextLine"/>
         <zone xml:id="smallform_0033_001_l_260"
               points="2706,2154 3564,2150 3564,2117 3485,2110 2706,2121"
               rendition="TextLine"/>
         <zone xml:id="smallform_0033_001_l_264"
               points="2702,2188 3473,2194 3559,2181 3560,2156 2966,2153 2917,2177 2703,2154"
               rendition="TextLine"/>
         <zone xml:id="smallform_0033_001_l_268"
               points="2702,2228 3568,2222 3552,2182 2702,2188"
               rendition="TextLine"/>
         <zone xml:id="smallform_0033_001_l_272"
               points="2698,2262 3560,2262 3572,2228 2699,2225"
               rendition="TextLine"/>
         <zone xml:id="smallform_0033_001_l_276"
               points="2700,2292 3561,2289 3547,2249 2700,2267"
               rendition="TextLine"/>
         <zone xml:id="smallform_0033_001_l_280"
               points="2700,2331 3559,2324 3537,2282 2700,2293"
               rendition="TextLine"/>
         <zone xml:id="smallform_0033_001_l_284"
               points="2700,2360 3571,2347 3541,2316 2700,2331"
               rendition="TextLine"/>
         <zone xml:id="smallform_0033_001_l_288"
               points="2700,2390 3571,2381 3561,2349 2700,2363"
               rendition="TextLine"/>
         <zone xml:id="smallform_0033_001_l_292"
               points="2700,2424 3568,2414 3545,2381 2700,2398"
               rendition="TextLine"/>
         <zone xml:id="smallform_0033_001_l_296"
               points="2704,2463 3569,2453 3552,2416 2704,2438"
               rendition="TextLine"/>
         <zone xml:id="smallform_0033_001_l_300"
               points="2700,2492 3568,2488 3541,2451 2700,2462"
               rendition="TextLine"/>
         <zone xml:id="smallform_0033_001_l_304"
               points="2698,2526 3568,2523 3545,2486 2698,2499"
               rendition="TextLine"/>
         <zone xml:id="smallform_0033_001_l_308"
               points="2698,2557 3558,2560 3558,2524 3526,2518 2698,2539"
               rendition="TextLine"/>
         <zone xml:id="smallform_0033_001_l_312"
               points="2706,2595 3546,2591 3546,2561 3498,2554 2706,2561"
               rendition="TextLine"/>
         <zone xml:id="smallform_0033_001_l_316"
               points="2703,2629 3564,2620 3564,2581 2703,2595"
               rendition="TextLine"/>
         <zone xml:id="smallform_0033_001_l_320"
               points="2699,2665 3563,2661 3563,2628 3484,2617 2699,2646"
               rendition="TextLine"/>
         <zone xml:id="smallform_0033_001_l_324"
               points="2701,2699 3558,2690 3537,2653 2701,2669"
               rendition="TextLine"/>
         <zone xml:id="smallform_0033_001_l_328"
               points="2697,2736 3557,2728 3549,2687 2698,2696"
               rendition="TextLine"/>
         <zone xml:id="smallform_0033_001_l_332"
               points="2697,2767 3564,2767 3564,2731 3507,2723 2697,2739"
               rendition="TextLine"/>
         <zone xml:id="smallform_0033_001_l_336"
               points="2701,2803 3562,2796 3537,2756 2701,2766"
               rendition="TextLine"/>
         <zone xml:id="smallform_0033_001_l_340"
               points="2699,2826 3583,2819 3482,2785 2699,2806"
               rendition="TextLine"/>
         <zone xml:id="smallform_0033_001_l_344"
               points="2709,2869 3560,2868 3553,2818 2709,2832"
               rendition="TextLine"/>
         <zone xml:id="smallform_0033_001_l_348"
               points="2704,2897 3548,2890 3528,2857 2706,2868"
               rendition="TextLine"/>
         <zone xml:id="smallform_0033_001_l_352"
               points="2699,2928 3560,2930 3560,2896 3505,2891 2699,2904"
               rendition="TextLine"/>
         <zone xml:id="smallform_0033_001_l_356"
               points="2693,2968 3569,2964 3505,2925 2693,2944"
               rendition="TextLine"/>
         <zone xml:id="smallform_0033_001_l_360"
               points="2711,3002 3564,2995 3565,2961 2712,2968"
               rendition="TextLine"/>
         <zone xml:id="smallform_0033_001_l_364"
               points="2704,3037 3564,3031 3558,2993 2704,3004"
               rendition="TextLine"/>
         <zone xml:id="smallform_0033_001_l_368"
               points="2701,3068 3567,3062 3567,3031 3525,3027 2701,3037"
               rendition="TextLine"/>
         <zone xml:id="smallform_0033_001_l_372"
               points="2701,3106 3558,3098 3558,3062 2701,3067"
               rendition="TextLine"/>
         <zone xml:id="smallform_0033_001_l_376"
               points="2696,3131 3569,3133 3569,3098 3494,3091 2696,3109"
               rendition="TextLine"/>
         <zone xml:id="smallform_0033_001_l_380"
               points="2713,3172 3563,3171 3571,3141 2713,3142"
               rendition="TextLine"/>
         <zone xml:id="smallform_0033_001_l_384"
               points="2703,3208 3568,3199 3539,3163 2703,3173"
               rendition="TextLine"/>
         <zone xml:id="smallform_0033_001_l_388"
               points="2693,3240 3502,3244 3570,3239 3571,3201 2693,3216"
               rendition="TextLine"/>
         <zone xml:id="smallform_0033_001_l_392"
               points="2699,3273 3241,3271 3299,3300 3572,3273 3560,3237 2699,3246"
               rendition="TextLine"/>
         <zone xml:id="smallform_0033_001_l_396"
               points="2683,3315 3570,3303 3551,3270 2683,3281"
               rendition="TextLine"/>
         <zone xml:id="smallform_0033_001_l_400"
               points="2692,3339 3569,3341 3538,3301 2692,3320"
               rendition="TextLine"/>
         <zone xml:id="smallform_0033_001_l_404"
               points="2701,3385 3055,3373 3035,3359 2991,3362 2961,3338 2950,3349 2876,3336 2852,3353 2796,3338 2701,3344"
               rendition="TextLine"/>
         <zone xml:id="smallform_0033_001_l_408"
               points="2744,3419 3560,3423 3560,3371 2744,3387"
               rendition="TextLine"/>
         <zone xml:id="smallform_0033_001_l_412"
               points="2707,3451 3567,3445 3517,3411 2782,3428 2707,3406"
               rendition="TextLine"/>
         <zone xml:id="smallform_0033_001_l_416"
               points="2709,3488 3564,3479 3564,3452 3499,3444 2709,3451"
               rendition="TextLine"/>
         <zone xml:id="smallform_0033_001_l_429"
               points="2699,3529 3558,3519 3568,3482 2700,3486"
               rendition="TextLine"/>
         <zone xml:id="smallform_0033_001_l_433"
               points="2700,3550 3578,3549 3537,3510 2700,3530"
               rendition="TextLine"/>
         <zone xml:id="smallform_0033_001_l_437"
               points="2697,3593 3446,3593 3568,3582 3569,3558 2698,3551"
               rendition="TextLine"/>
         <zone xml:id="smallform_0033_001_l_446"
               points="2703,3617 3564,3614 3521,3579 2703,3593"
               rendition="TextLine"/>
         <zone xml:id="smallform_0033_001_l_442"
               points="2695,3657 3567,3655 3551,3611 2695,3622"
               rendition="TextLine"/>
         <zone xml:id="smallform_0033_001_l_450"
               points="2708,3688 3561,3682 3547,3649 2708,3657"
               rendition="TextLine"/>
         <zone xml:id="smallform_0033_001_l_454"
               points="2704,3723 3559,3718 3548,3679 2704,3688"
               rendition="TextLine"/>
         <zone xml:id="smallform_0033_001_l_458"
               points="2712,3761 3558,3760 3559,3718 3498,3714 2713,3724"
               rendition="TextLine"/>
         <zone xml:id="smallform_0033_001_l_462"
               points="2701,3796 3558,3787 3558,3758 3515,3753 2701,3769"
               rendition="TextLine"/>
         <zone xml:id="smallform_0033_001_l_466"
               points="2703,3825 3565,3818 3545,3784 2703,3796"
               rendition="TextLine"/>
         <zone xml:id="smallform_0033_001_l_470"
               points="2703,3861 3558,3854 3547,3816 2704,3826"
               rendition="TextLine"/>
         <zone xml:id="smallform_0033_001_l_474"
               points="2706,3895 3561,3885 3547,3850 2706,3860"
               rendition="TextLine"/>
         <zone xml:id="smallform_0033_001_l_478"
               points="2700,3928 3514,3927 3565,3889 2700,3894"
               rendition="TextLine"/>
         <zone xml:id="smallform_0033_001_l_482"
               points="2703,3963 3564,3951 3551,3918 2704,3926"
               rendition="TextLine"/>
         <zone xml:id="smallform_0033_001_l_486"
               points="2706,3994 3568,3990 3568,3958 3496,3949 2706,3963"
               rendition="TextLine"/>
         <zone xml:id="smallform_0033_001_l_490"
               points="2704,4044 3564,4032 3551,3990 2706,3993"
               rendition="TextLine"/>
      </zone>
   </surface>
   <surface xml:id="smallform_0033_002_facs"
            ulx="0"
            uly="0"
            lrx="3648"
            lry="5512">
      <graphic url="https://iiif.ub.unibe.ch/image/v3/schwarzenbach/smallform_0033_002.png/info.json"
               width="3648"
               height="5512"/>
      <zone xml:id="smallform_0033_002_r"
            points="102,1046 105,105 960,105 960,1037 960,1095 909,1095 105,1095"
            rendition="TextRegion">
         <zone xml:id="smallform_0033_002_l"
               points="112,149 948,165 948,117 909,108 302,104 241,136 188,99 112,107"
               rendition="TextLine"/>
         <zone xml:id="smallform_0033_002_l_7"
               points="112,181 947,197 947,166 871,151 839,172 112,150"
               rendition="TextLine"/>
         <zone xml:id="smallform_0033_002_l_11"
               points="108,217 912,234 958,225 957,196 107,189"
               rendition="TextLine"/>
         <zone xml:id="smallform_0033_002_l_15"
               points="104,254 950,262 921,227 104,219"
               rendition="TextLine"/>
         <zone xml:id="smallform_0033_002_l_19"
               points="107,289 948,295 948,261 892,255 709,279 107,251"
               rendition="TextLine"/>
         <zone xml:id="smallform_0033_002_l_23"
               points="104,320 950,335 944,295 104,297"
               rendition="TextLine"/>
         <zone xml:id="smallform_0033_002_l_27"
               points="104,351 938,379 950,336 103,323"
               rendition="TextLine"/>
         <zone xml:id="smallform_0033_002_l_31"
               points="95,381 837,404 813,361 95,365"
               rendition="TextLine"/>
         <zone xml:id="smallform_0033_002_l_35"
               points="154,417 948,431 947,394 915,388 839,412 154,396"
               rendition="TextLine"/>
         <zone xml:id="smallform_0033_002_l_39"
               points="103,457 914,472 944,468 943,432 102,423"
               rendition="TextLine"/>
         <zone xml:id="smallform_0033_002_l_43"
               points="104,490 950,497 950,471 899,463 104,458"
               rendition="TextLine"/>
         <zone xml:id="smallform_0033_002_l_47"
               points="98,522 955,537 955,500 890,493 98,502"
               rendition="TextLine"/>
         <zone xml:id="smallform_0033_002_l_51"
               points="108,556 896,575 949,571 948,534 107,523"
               rendition="TextLine"/>
         <zone xml:id="smallform_0033_002_l_55"
               points="104,586 951,600 928,564 104,557"
               rendition="TextLine"/>
         <zone xml:id="smallform_0033_002_l_59"
               points="102,619 933,642 950,604 656,618 450,588 419,618 101,590"
               rendition="TextLine"/>
         <zone xml:id="smallform_0033_002_l_63"
               points="101,660 956,672 955,640 917,634 100,626"
               rendition="TextLine"/>
         <zone xml:id="smallform_0033_002_l_67"
               points="102,691 953,698 923,666 102,661"
               rendition="TextLine"/>
         <zone xml:id="smallform_0033_002_l_71"
               points="105,730 953,736 927,700 104,691"
               rendition="TextLine"/>
         <zone xml:id="smallform_0033_002_l_75"
               points="95,755 956,771 955,741 896,728 95,729"
               rendition="TextLine"/>
         <zone xml:id="smallform_0033_002_l_79"
               points="107,795 899,809 948,801 948,769 106,764"
               rendition="TextLine"/>
         <zone xml:id="smallform_0033_002_l_83"
               points="100,829 957,840 940,803 100,794"
               rendition="TextLine"/>
         <zone xml:id="smallform_0033_002_l_87"
               points="93,857 950,876 950,842 898,837 93,838"
               rendition="TextLine"/>
         <zone xml:id="smallform_0033_002_l_91"
               points="100,897 924,914 951,876 341,862 306,887 99,858"
               rendition="TextLine"/>
         <zone xml:id="smallform_0033_002_l_95"
               points="100,931 953,941 914,905 100,897"
               rendition="TextLine"/>
         <zone xml:id="smallform_0033_002_l_99"
               points="98,962 946,979 946,940 97,931"
               rendition="TextLine"/>
         <zone xml:id="smallform_0033_002_l_103"
               points="98,1002 949,1016 929,973 98,962"
               rendition="TextLine"/>
         <zone xml:id="smallform_0033_002_l_107"
               points="98,1039 958,1039 855,1006 98,997"
               rendition="TextLine"/>
         <zone xml:id="smallform_0033_002_l_112"
               points="452,1088 518,1075 539,1089 709,1090 736,1076 912,1091 900,1040 452,1041"
               rendition="TextLine"/>
      </zone>
   </surface>
</facsimile>
